qtuidoctools/__init__.py
qtuidoctools/__main__.py
qtuidoctools/_version.py
qtuidoctools/cli_utils.py
qtuidoctools/keymap_db.py
qtuidoctools/merge_utils.py
qtuidoctools/qtui.py
qtuidoctools/qtuibuild.py
qtuidoctools/textutils.py
qtuidoctools/update_worker.py
qtuidoctools-2.0.3.dist-info/METADATA
qtuidoctools-2.0.3.dist-info/WHEEL
qtuidoctools-2.0.3.dist-info/entry_points.txt
qtuidoctools-2.0.3.dist-info/licenses/LICENSE
qtuidoctools-2.0.3.dist-info/RECORD
