Metadata-Version: 2.4
Name: qtuidoctools
Version: 2.0.3
Summary: Tools for working with Qt .ui files
Project-URL: Homepage, https://twardoch.github.io/qtuidoctools/
Project-URL: Source, https://github.com/twardoch/qtuidoctools
Project-URL: Issues, https://github.com/twardoch/qtuidoctools/issues
Author-email: Adam Twardoch <adam+github@twardoch.com>
License-Expression: MIT
License-File: LICENSE
Keywords: cli,documentation,json,qt,ui,yaml
Classifier: Development Status :: 4 - Beta
Classifier: Environment :: Console
Classifier: License :: OSI Approved :: MIT License
Classifier: Programming Language :: Python :: 3
Classifier: Programming Language :: Python :: 3.11
Classifier: Programming Language :: Python :: 3.12
Classifier: Programming Language :: Python :: 3.13
Classifier: Topic :: Software Development :: Documentation
Classifier: Topic :: Text Processing :: Markup :: XML
Requires-Python: >=3.11
Requires-Dist: fire>=0.5.0
Requires-Dist: loguru>=0.7.2
Requires-Dist: lxml>=4.4.1
Requires-Dist: pyyaml>=5.1.1
Requires-Dist: qt-py>=1.2.1
Requires-Dist: rich>=13.7
Requires-Dist: yaplon
Provides-Extra: dev
Requires-Dist: mypy>=1.0; extra == 'dev'
Requires-Dist: pytest-cov>=4.0; extra == 'dev'
Requires-Dist: pytest>=7.0; extra == 'dev'
Requires-Dist: ruff>=0.6.0; extra == 'dev'
